dmactr.v
`include "define.h"

module dmactr (
	// Signals between DMAC and devices
	output reg [`BUS_ADDR_WIDTH-1:0] addr,	// Memory or I/O address
	output reg [`DATA_WIDTH-1:0] odata,	// Write data
	input [`DATA_WIDTH-1:0] idata,		// Read data
	output reg rw_,				// Read/write signal
	// Signals between DMAC and bus arbiter
	output reg breq_,			// Bus request
	input bgrt_,				// Bus grant

	input [`BUS_ADDR_WIDTH-1:0] dsaddr,// DMA source address
	input [`BUS_ADDR_WIDTH-1:0] ddaddr,// DMA destination address
	input [1:0] dmode, // DMA transfer mode
	input dreq_, // DMA request (*)
	output reg eop_, // DMA complete
	input reset_, input clk
);

localparam BURST_SIZE = 4;

reg [1:0] state;
reg [1:0] count;                        // word counter for burst
reg [`BUS_ADDR_WIDTH-1:0] src, dst;     // current src/dst addresses

always @ (posedge clk)
	if (reset_ == `Enable_) begin
		eop_  <= `Disable_;
		breq_ <= `Disable_;
		rw_   <= `Write;
		odata <= 0;
		addr  <= 0;
		count <= 0;
		src   <= 0;
		dst   <= 0;
		state <= `WAIT;
	end else begin
		case (state)
		`WAIT: begin
			if (dreq_ == `Enable_) begin
				breq_ <= `Enable_;
				src   <= dsaddr;   // latch addresses at request time
				dst   <= ddaddr;
				count <= 0;
				state <= `READ1;
			end
			eop_ <= `Disable_;
		end
		`READ1: begin
			if (bgrt_ == `Enable_) begin
				addr  <= src;
				rw_   <= `Read;
				state <= `WRITE1;
			end
		end
		`WRITE1: begin
			addr  <= dst;
			rw_   <= `Write;
			odata <= idata;
			if (dmode == 2'b00 || count == BURST_SIZE - 1) begin
				// single mode, or last word of burst
				state <= `DONE;
			end else begin
				// increment addresses for next burst word
				if (dmode == 2'b01 || dmode == 2'b10) src <= src + 1;
				if (dmode == 2'b01 || dmode == 2'b11) dst <= dst + 1;
				count <= count + 1;
				state <= `READ1;
			end
		end
		`DONE: begin
			eop_  <= `Enable_;
			breq_ <= `Disable_;
			state <= `WAIT;
		end
		endcase
	end

endmodule

busarb.v
`include "define.h"

module busarb (
	// Bus request/grant for initiators 1 and 2
	input breq0_, input breq1_, output bgrt0_, output bgrt1_,
	input reset_, input clk
);

reg state;

assign bgrt0_ = (state == `BGRT0) ? `Enable_ : `Disable_;
assign bgrt1_ = (state == `BGRT0) ? `Enable_ : `Disable_;

always @ (posedge clk)
	if (reset_ == `Enable_) begin
		state <= `BGRT0;
		// State register should be initialized
	end else begin
		case (state)
		`BGRT0: if (breq0_ == `Disable_ && breq1_ == `Enable_)
				state <= `BGRT1;
		`BGRT1: if (breq1_ == `Disable_ && breq0_ == `Enable_)
				state <= `BGRT0;
		endcase
	end

endmodule

timer.v
`include "define.h"

module timer (
	input [`MEM_ADDR_WIDTH-1:0] addr,
	input [`DATA_WIDTH-1:0] idata,
	output [`DATA_WIDTH-1:0] odata,
	input cs_, input rw_, input clk
);

reg [31:0] count;
reg en;
wire clear, start, stop;

assign clear = (cs_ == `Enable_ && rw_ == `Write && addr == 4 && idata == 1);
assign start = (cs_ == `Enable_ && rw_ == `Write && addr == 4 && idata == 2);
assign stop = (cs_ == `Enable_ && rw_ == `Write && addr == 4 && idata == 4);

always @ (posedge clk)
	if (clear) count <= 0;
	else if (en) count <= count + 1;

always @ (posedge clk)
	if (start) en <= `Enable;
	 else if (stop) en <= `Disable;

assign odata = (addr == 0) ? count[7:0] : 
							(addr == 1) ? count[15:8] : 
							(addr == 2) ? count[23:16] : 
							(addr == 3) ? count[31:24] : 0;
endmodule

sram.v
`include "define.h"

module sram (
	// Memory address
	input [`MEM_ADDR_WIDTH-1:0] addr,
	// Input data and output data
	input [`DATA_WIDTH-1:0] idata,
	output [`DATA_WIDTH-1:0] odata,
	// Control signals (chip select, read/write, and clock)
	input cs_, input rw_, input clk
);

reg [`DATA_WIDTH-1:0] mem [(1<<`MEM_ADDR_WIDTH)-1:0];

assign odata = (rw_ == `Read && cs_ ==`Enable_) ? mem[addr] : 0;

always @ (posedge clk)
	if (cs_ == `Enable_ && rw_ == `Write) 
			mem[addr] <= idata;

endmodule

addrdec.v
`include "define.h"
module addrdec (
	// Memory address
	input [`BUS_ADDR_WIDTH-1:0] addr,
	// Four chip select signals (active-low)
	output cs0_, output cs1_, output cs2_, output cs3_
);

assign cs0_ = ~(addr[9:8] == 2'b00);
assign cs1_ = ~(addr[9:8] == 2'b01);
assign cs2_ = ~(addr[9:8] == 2'b10);
assign cs3_ = ~(addr[9:8] == 2'b11);

endmodule

devices.v
`include "define.h"

module devices (
	input [`BUS_ADDR_WIDTH-1:0] addr,
	input [`DATA_WIDTH-1:0] idata,
	output [`DATA_WIDTH-1:0] odata,
	input rw_, input reset_, input clk
);

wire [`DATA_WIDTH-1:0] odata0, odata1, odata2;
wire cs0_, cs1_, cs2_, cs3_;

addrdec u0 (addr, cs0_, cs1_, cs2_, cs3_);
sram u1 (addr[`MEM_ADDR_WIDTH-1:0], idata, odata0, cs0_, rw_, clk);
sram u2 (addr[`MEM_ADDR_WIDTH-1:0], idata, odata1, cs1_, rw_, clk);
timer u3 (addr[`MEM_ADDR_WIDTH-1:0], idata, odata2, cs2_, rw_, clk);

assign odata =	(cs0_ == `Enable_) ? odata0 :
		(cs1_ == `Enable_) ? odata1 :
		(cs2_ == `Enable_) ? odata2 : 0;

endmodule

top.v
`include "define.h"

module top (
	// Initiator 1
	input [`BUS_ADDR_WIDTH-1:0] addr0,
	input [`DATA_WIDTH-1:0] idata0,
	output [`DATA_WIDTH-1:0] odata0,
	input rw0_, input breq0_, output bgrt0_,
	input [`BUS_ADDR_WIDTH-1:0] dsaddr, // DMA source address
	input [`BUS_ADDR_WIDTH-1:0] ddaddr, // DMA destination address
	input [1:0] dmode, // DMA transfer mode
	input dreq_, // DMA request (*)
	output eop_, // DMA complete
	input reset_, input clk,	
);	

// Initiator 2
wire [`BUS_ADDR_WIDTH-1:0] addr1;
wire [`DATA_WIDTH-1:0] idata1;
wire [`DATA_WIDTH-1:0] odata1;
wire rw1_, breq1_, bgrt1_;

wire [`BUS_ADDR_WIDTH-1:0] addr;
wire [`DATA_WIDTH-1:0] idata, odata;
wire rw_;

assign odata0 = odata;
assign odata1 = odata;
assign addr   = (bgrt0_ ==`Enable_) ? addr0:addr1;// addr0 or addr1 depending on bgrt
assign idata  = (bgrt0_ ==`Enable_) ? idata0:idata1;// idata0 or idata1 depending on bgrt
assign rw_    = (bgrt0_ ==`Enable_) ? rw0_:rw1_;// rw0_ or rw1_ depending on bgrt

devices u0 (addr, idata, odata, rw_, reset_, clk);
busarb u1 (breq0_, breq1_, bgrt0_, bgrt1_, reset_, clk);
dmactr u2 (addr1, idata1, odata1, rw1_, breq1_, bgrt1_, 
			dsaddr, ddaddr, dmode, dreq_, eop_, reset_, clk);
endmodule

test.v
`timescale 1ns/10ps
`include "define.h"

module test ();

reg [`BUS_ADDR_WIDTH-1:0] addr0;
reg [`DATA_WIDTH-1:0] idata0;
wire [`DATA_WIDTH-1:0] odata0;
reg rw0_, breq0_, dreq_;
wire bgrt0_, eop_;
reg [`BUS_ADDR_WIDTH-1:0] dsaddr, ddaddr;
reg [1:0] dmode;
reg reset_, clk;

top u0 (addr0, idata0, odata0, rw0_, breq0_, bgrt0_, dsaddr, ddaddr, dmode, dreq_, eop_, reset_, clk);

always begin
	clk <= 1; #1;
	clk <= 0; #1;
end

initial begin
	#1;
	$dumpfile("dump.vcd");
	$dumpvars(0, test.u0);

	// initialize all signals to known state before reset
	addr0  = 0;
	idata0 = 0;
	rw0_   = `Read;
	breq0_ = `Disable_;
	dreq_  = `Disable_;
	dsaddr = 0;
	ddaddr = 0;
	dmode  = 2'b00;

	// 1. Reset
	reset_ = `Enable_;
	repeat(3) @(posedge clk);
	reset_ = `Disable_;
	@(posedge clk);

	// 2. Memory write by CPU (initiator 1): write 0x99 to 0x150
	// bgrt0_ is already Enable_ after reset (busarb starts in BGRT0)
	breq0_ = `Enable_;
	@(posedge clk);
	addr0  = 10'h150;
	idata0 = 8'h99;
	rw0_   = `Write;
	@(posedge clk);        // SRAM writes at this edge

	// 3. Memory read by CPU (initiator 1): verify write succeeded
	rw0_   = `Read;
	#1;                    // combinational propagation
	$display("Read  0x150 = 0x%h  (expect 0x99)", odata0);
	breq0_ = `Disable_;
	@(posedge clk);

	// 4. Data transfer by DMAC (initiator 2): burst M->M, 0x150-0x153 -> 0x160-0x163
	// breq0_ must be de-asserted so DMAC can win bus arbitration
	dsaddr = 10'h150;
	ddaddr = 10'h160;
	dmode  = 2'b00;        // burst memory-to-memory
	dreq_  = `Enable_;
	@(posedge clk);        // DMAC sees dreq_, asserts breq_
	dreq_  = `Disable_;    // de-assert immediately to prevent re-trigger
	@(negedge eop_);       // wait for DMA transfer complete (eop_ goes low)
	@(posedge clk);

	// 5. Memory read by CPU (initiator 1): verify DMA transfer to 0x160
	breq0_ = `Enable_;
	@(negedge bgrt0_);     // wait until CPU gets bus grant back
	addr0  = 10'h160;
	rw0_   = `Read;
	#1;                    // combinational propagation
	$display("Read  0x160 = 0x%h  (expect 0x99)", odata0);
	breq0_ = `Disable_;
	repeat(2) @(posedge clk);

	$finish;
end

endmodule

dump.vcd
$date
	Tue May 26 17:05:42 2026
$end
$version
	Icarus Verilog
$end
$timescale
	10ps
$end
$scope module test $end
$scope module u0 $end
$var wire 10 ! addr0 [9:0] $end
$var wire 1 " breq0_ $end
$var wire 1 # clk $end
$var wire 10 $ ddaddr [9:0] $end
$var wire 2 % dmode [1:0] $end
$var wire 1 & dreq_ $end
$var wire 10 ' dsaddr [9:0] $end
$var wire 8 ( idata0 [7:0] $end
$var wire 8 ) odata0 [7:0] $end
$var wire 8 * odata1 [7:0] $end
$var wire 1 + reset_ $end
$var wire 1 , rw0_ $end
$var wire 1 - rw_ $end
$var wire 1 . rw1_ $end
$var wire 8 / odata [7:0] $end
$var wire 8 0 idata1 [7:0] $end
$var wire 8 1 idata [7:0] $end
$var wire 1 2 eop_ $end
$var wire 1 3 breq1_ $end
$var wire 1 4 bgrt1_ $end
$var wire 1 5 bgrt0_ $end
$var wire 10 6 addr1 [9:0] $end
$var wire 10 7 addr [9:0] $end
$scope module u0 $end
$var wire 10 8 addr [9:0] $end
$var wire 1 # clk $end
$var wire 8 9 idata [7:0] $end
$var wire 1 + reset_ $end
$var wire 1 - rw_ $end
$var wire 8 : odata2 [7:0] $end
$var wire 8 ; odata1 [7:0] $end
$var wire 8 < odata0 [7:0] $end
$var wire 8 = odata [7:0] $end
$var wire 1 > cs3_ $end
$var wire 1 ? cs2_ $end
$var wire 1 @ cs1_ $end
$var wire 1 A cs0_ $end
$scope module u0 $end
$var wire 10 B addr [9:0] $end
$var wire 1 A cs0_ $end
$var wire 1 @ cs1_ $end
$var wire 1 ? cs2_ $end
$var wire 1 > cs3_ $end
$upscope $end
$scope module u1 $end
$var wire 8 C addr [7:0] $end
$var wire 1 # clk $end
$var wire 1 A cs_ $end
$var wire 8 D idata [7:0] $end
$var wire 1 - rw_ $end
$var wire 8 E odata [7:0] $end
$upscope $end
$scope module u2 $end
$var wire 8 F addr [7:0] $end
$var wire 1 # clk $end
$var wire 1 @ cs_ $end
$var wire 8 G idata [7:0] $end
$var wire 1 - rw_ $end
$var wire 8 H odata [7:0] $end
$upscope $end
$scope module u3 $end
$var wire 8 I addr [7:0] $end
$var wire 1 J clear $end
$var wire 1 # clk $end
$var wire 1 ? cs_ $end
$var wire 8 K idata [7:0] $end
$var wire 1 - rw_ $end
$var wire 1 L start $end
$var wire 1 M stop $end
$var wire 8 N odata [7:0] $end
$var reg 32 O count [31:0] $end
$var reg 1 P en $end
$upscope $end
$upscope $end
$scope module u1 $end
$var wire 1 " breq0_ $end
$var wire 1 # clk $end
$var wire 1 + reset_ $end
$var wire 1 3 breq1_ $end
$var wire 1 4 bgrt1_ $end
$var wire 1 5 bgrt0_ $end
$var reg 1 Q state $end
$upscope $end
$scope module u2 $end
$var wire 1 4 bgrt_ $end
$var wire 1 # clk $end
$var wire 10 R ddaddr [9:0] $end
$var wire 2 S dmode [1:0] $end
$var wire 1 & dreq_ $end
$var wire 10 T dsaddr [9:0] $end
$var wire 8 U idata [7:0] $end
$var wire 1 + reset_ $end
$var parameter 32 V BURST_SIZE $end
$var reg 10 W addr [9:0] $end
$var reg 1 3 breq_ $end
$var reg 2 X count [1:0] $end
$var reg 10 Y dst [9:0] $end
$var reg 1 2 eop_ $end
$var reg 8 Z odata [7:0] $end
$var reg 1 . rw_ $end
$var reg 10 [ src [9:0] $end
$var reg 2 \ state [1:0] $end
$upscope $end
$upscope $end
$upscope $end
$enddefinitions $end
$comment Show the parameter values. $end
$dumpall
b100 V
$end
#100
$dumpvars
bx \
bx [
bx Z
bx Y
bx X
bx W
bx U
b0 T
b0 S
b0 R
xQ
xP
bx O
bx N
xM
xL
bx K
xJ
bx I
bx H
bx G
bx F
bx E
bx D
bx C
bx B
xA
x@
x?
x>
bx =
bx <
bx ;
bx :
bx 9
bx 8
bx 7
bx 6
x5
x4
x3
x2
bx 1
bx 0
bx /
x.
x-
1,
0+
bx *
bx )
b0 (
b0 '
1&
b0 %
b0 $
0#
1"
b0 !
$end
#200
b0 ;
b0 H
0A
1@
1?
1>
1-
b0 C
b0 F
b0 I
0J
0L
0M
05
14
b0 7
b0 8
b0 B
b0 1
b0 9
b0 D
b0 G
b0 K
b0 \
b0 Y
b0 [
b0 X
b0 6
b0 W
b0 0
b0 Z
0.
13
12
0Q
1#
#300
0#
#400
1#
#500
0#
#600
1+
1#
#700
0#
#800
0"
1#
#900
0#
#1000
b0 *
b0 U
b0 )
b0 /
b0 =
b0 <
b0 E
b0 :
b0 N
1A
0@
b1010000 C
b1010000 F
b1010000 I
0-
b10011001 1
b10011001 9
b10011001 D
b10011001 G
b10011001 K
b101010000 7
b101010000 8
b101010000 B
0,
b10011001 (
b101010000 !
1#
#1100
0#
#1200
b10011001 *
b10011001 U
b10011001 )
b10011001 /
b10011001 =
b10011001 ;
b10011001 H
1-
1,
1#
#1300
0#
1"
#1400
b1 \
b101100000 Y
b101010000 [
03
0&
b101100000 $
b101100000 R
b101010000 '
b101010000 T
1#
#1500
0#
#1600
b0 *
b0 U
b0 )
b0 /
b0 =
b0 ;
b0 H
bx :
bx N
0A
1@
b0 C
b0 F
b0 I
0-
b0 1
b0 9
b0 D
b0 G
b0 K
b0 7
b0 8
b0 B
15
04
1Q
1&
1#
#1700
0#
#1800
b10011001 *
b10011001 U
b10011001 )
b10011001 /
b10011001 =
b10011001 ;
b10011001 H
b0 <
b0 E
b0 :
b0 N
1A
0@
b1010000 C
b1010000 F
b1010000 I
1-
b101010000 7
b101010000 8
b101010000 B
b10 \
1.
b101010000 6
b101010000 W
1#
#1900
0#
#2000
b0 *
b0 U
b0 )
b0 /
b0 =
b0 ;
b0 H
b1100000 C
b1100000 F
b1100000 I
b10011001 1
b10011001 9
b10011001 D
b10011001 G
b10011001 K
0-
b101100000 7
b101100000 8
b101100000 B
b11 \
b10011001 0
b10011001 Z
0.
b101100000 6
b101100000 W
1#
#2100
0#
#2200
b0 \
13
02
1#
#2300
0#
#2400
b10011001 *
b10011001 U
b10011001 )
b10011001 /
b10011001 =
b10011001 ;
b10011001 H
1-
b101100000 !
05
14
0Q
12
0"
1#
#2500
0#
1"
